License
pyproject.toml
setup.py
pack1/Guess.py
pack1/__init__.py
pack1/cowBulls.py
pack1/rockspaper.py
pythonGames/__init__.py
pythonGames/pack1/Guess.py
pythonGames/pack1/__init__.py
pythonGames/pack1/cowBulls.py
pythonGames/pack1/rockspaper.py
ulla_python_games.egg-info/PKG-INFO
ulla_python_games.egg-info/SOURCES.txt
ulla_python_games.egg-info/dependency_links.txt
ulla_python_games.egg-info/top_level.txt