Metadata-Version: 2.4
Name: ulla_python_games
Version: 0.1.0
Summary: A collection of Python games for learning and fun
Author: Afnan
Author-email: afnan.ulla@synechron.com
Classifier: Programming Language :: Python :: 3
Classifier: License :: OSI Approved :: MIT License
Classifier: Operating System :: OS Independent
Requires-Python: >=3.6
License-File: License
Dynamic: author
Dynamic: author-email
Dynamic: classifier
Dynamic: description
Dynamic: description-content-type
Dynamic: license-file
Dynamic: requires-python
Dynamic: summary
